MANIFEST.in
README.md
environment.yml
pyREADME.md
setup.py
gcp/bigquery/bundle_error.sql
gcp/bigquery/bundle_pass.sql
gcp/bigquery/pat_everything_error.sql
gcp/bigquery/pat_everything_pass.sql
gcp/bigquery/postgres_to_bq/bq_create_fhir_tables.sql
gcp/bigquery/postgres_to_bq/bq_load_fhir_tables.sh
gcp/bigquery/postgres_to_bq/psql_export_fhir_to_csv.sql
gcp/functions/bundle_processor/main.py
gcp/functions/bundle_processor/requirements.txt
gcp/functions/patient_everything/main.py
gcp/functions/patient_everything/requirements.txt
py_mimic_fhir/__init__.py
py_mimic_fhir/__main__.py
py_mimic_fhir/bundle.py
py_mimic_fhir/config.py
py_mimic_fhir/db.py
py_mimic_fhir/io.py
py_mimic_fhir/lookup.py
py_mimic_fhir/terminology.py
py_mimic_fhir/validate.py
py_mimic_fhir.egg-info/PKG-INFO
py_mimic_fhir.egg-info/SOURCES.txt
py_mimic_fhir.egg-info/dependency_links.txt
py_mimic_fhir.egg-info/requires.txt
py_mimic_fhir.egg-info/top_level.txt
py_mimic_fhir/scripts/sort_ndjson.sh