Metadata-Version: 2.1
Name: py-mimic-fhir
Version: 1.0.0
Summary: A package to help convert MIMIC-IV to FHIR
Home-page: https://github.com/kind-lab/mimic-fhir
Author: Alex Bennett
Author-email: alexmbennett2@gmail.com
License: UNKNOWN
Platform: UNKNOWN
Requires-Python: >=3.8
